replication/__init__.py
replication/constants.py
replication/exception.py
replication/interface.py
replication/objects.py
replication/porcelain.py
replication/protocol.py
replication/repository.py
replication/server.py
replication/ttl.py
replication/utils.py
replication-0.9.10.dist-info/LICENSE
replication-0.9.10.dist-info/METADATA
replication-0.9.10.dist-info/WHEEL
replication-0.9.10.dist-info/entry_points.txt
replication-0.9.10.dist-info/top_level.txt
replication-0.9.10.dist-info/RECORD
