Metadata-Version: 2.1
Name: replication
Version: 0.9.10
Summary: A prototype object replication lib
Home-page: https://gitlab.com/slumber/replication
Author: Swann Martinez
Author-email: swann.martinez@pm.me
License: GPL3
License-File: LICENSE
Requires-Dist: pyzmq==25.0.2
Requires-Dist: deepdiff==5.7.0
